zotero_mcp/__init__.py
zotero_mcp/cli.py
zotero_mcp/client.py
zotero_mcp-0.1.6.dist-info/METADATA
zotero_mcp-0.1.6.dist-info/WHEEL
zotero_mcp-0.1.6.dist-info/entry_points.txt
zotero_mcp-0.1.6.dist-info/licenses/LICENSE
zotero_mcp-0.1.6.dist-info/RECORD
