Metadata-Version: 2.4
Name: zotero-mcp
Version: 0.1.6
Summary: Model Context Protocol server for Zotero
Project-URL: Repository, https://github.com/kujenga/zotero-mcp
Project-URL: Issues, https://github.com/kujenga/zotero-mcp/issues
Author-email: Aaron Taylor <pypi@ataylor.io>
License: MIT License
License-File: LICENSE
Keywords: mcp,zotero
Classifier: Intended Audience :: Developers
Classifier: License :: OSI Approved :: MIT License
Classifier: Operating System :: OS Independent
Classifier: Programming Language :: Python :: 3 :: Only
Classifier: Programming Language :: Python :: 3.11
Classifier: Programming Language :: Python :: 3.12
Classifier: Programming Language :: Python :: 3.13
Requires-Python: >=3.11
Requires-Dist: mcp[cli]>=1.2.1
Requires-Dist: pydantic>=2.10.6
Requires-Dist: python-dotenv>=1.0.1
Requires-Dist: pyzotero>=1.6.8
